{
  "allowedLicenses": [
    {
      "moduleLicense": "Apache-2.0",
      "moduleName": ".*"
    },
    {
      "moduleLicense": "MIT",
      "moduleName": ".*"
    },
    {
      "moduleLicense": "MIT-OneJar",
      "moduleName": ".*"
    },
    {
      "moduleLicense": "BSD-0-Clause",
      "moduleVersion": ".*"
    },
    {
      "moduleLicense": "BSD-2-Clause",
      "moduleVersion": ".*"
    },
    {
      "moduleLicense": "BSD-3-Clause",
      "moduleVersion": ".*"
    },
    {
      "moduleLicense": "BSD-3-Clause-Nuclear",
      "moduleVersion": ".*"
    },
    {
      "moduleLicense": "CUP-Parser",
      "moduleVersion": "11b-20160615",
      "moduleName": "com.github.vbmacher:java-cup-runtime"
    },
    {
      "moduleLicense": "CDDL-1.0",
      "moduleVersion": ".*",
      "moduleName": "javax.servlet:javax.servlet-api"
    },
    {
      "moduleLicense": "Bouncy-Castle",
      "moduleVersion": ".*",
      "moduleName": "org.bouncycastle:.*"
    },
    {
      "moduleLicense": "Eclipse-Distribution-1.0",
      "moduleVersion": ".*"
    },
    {
      "moduleLicense": "Eclipse-Public-2.0",
      "moduleVersion": ".*"
    },
    {
      "moduleLicense": "Eclipse-Public-1.0",
      "moduleVersion": ".*"
    },
    {
      "moduleLicense": "Mozilla-1.1",
      "moduleVersion": ".*"
    },
    {
      "moduleLicense": "CC0-1.0",
      "moduleVersion": ".*"
    },
    {
      "moduleLicense": "Public-Domain",
      "moduleVersion": "1.9",
      "moduleName": "org.tukaani:xz"
    },
    {
      "moduleLicense": "UnRar",
      "moduleVersion": "7.5.5",
      "moduleName": "com.github.junrar:junrar"
    },
    {
      "moduleLicense": "CDDL-1.0",
      "moduleVersion": "1.1.0",
      "moduleName": "org.codelibs:jhighlight"
    },
    {
      "moduleLicense": "Apache-1.0-no-acknowledge",
      "moduleVersion": "2.0.6.1",
      "moduleName": "org.jdom:jdom2"
    },
    {
      "moduleLicense": null,
      "moduleVersion": "2.13.4",
      "moduleName": "com.fasterxml.jackson:jackson-bom"
    },
    {
      "moduleLicense": "ISC",
      "moduleName": ".*"
    }
  ]
}